{
  "kind": "collectionType",
  "collectionName": "pages",
  "info": {
    "singularName": "page",
    "pluralName": "pages",
    "displayName": "page",
    "description": ""
  },
  "options": {
    "draftAndPublish": true
  },
  "pluginOptions": {
    "i18n": {
      "localized": true
    }
  },
  "attributes": {
    "slug": {
      "pluginOptions": {
        "i18n": {
          "localized": true
        }
      },
      "type": "string",
      "unique": true
    },
    "category": {
      "type": "relation",
      "relation": "manyToOne",
      "target": "api::category.category",
      "inversedBy": "pages"
    },
    "label": {
      "pluginOptions": {
        "i18n": {
          "localized": true
        }
      },
      "type": "string"
    },
    "pageSections": {
      "pluginOptions": {
        "i18n": {
          "localized": true
        }
      },
      "type": "dynamiczone",
      "components": [
        "sections.hero-banner",
        "sections.rich-text",
        "sections.info-cards-type-a",
        "sections.image-banner",
        "sections.blocks-grid",
        "sections.columns",
        "sections.columns-with-tabs"
      ]
    }
  }
}
